{
  "resourceType": "StructureDefinition",
  "extension": [
    {
      "url": "http://www.fragment.com/mapname",
      "valueString": "Tumor Satellite/Fragment"
    },
    {
      "url": "http://www.fragment.com/Group",
      "valueString": "Fragment/TumorSatelliteFragment"
    },
    {
      "url": "http://www.fragment.com/isFragment",
      "valueBoolean": true
    },
    {
      "url": "http://www.fragment.com/fragment",
      "valueUrl": "http://hl7.org/fhir/us/breast-radiology/StructureDefinition/HeaderFragment"
    },
    {
      "url": "http://www.fragment.com/maplink",
      "valueString": "{\r\n  \"LinkType\": \"fragment\",\r\n  \"ShowChildren\": false,\r\n  \"LinkTarget\": \"http://hl7.org/fhir/us/breast-radiology/StructureDefinition/HeaderFragment\"\r\n}"
    },
    {
      "url": "http://www.fragment.com/maplink",
      "valueString": "{\r\n  \"LinkType\": \"extension\",\r\n  \"ShowChildren\": true,\r\n  \"Cardinality\": \"0..1\",\r\n  \"ComponentHRef\": \"StructureDefinition-{SDName}-definitions.html#Observation.extension:tumorSatellite\",\r\n  \"LocalName\": \"Tumor Satellite\",\r\n  \"LinkTarget\": \"http://hl7.org/fhir/us/breast-radiology/StructureDefinition/TumorSatelliteExtension\"\r\n}"
    }
  ],
  "url": "http://hl7.org/fhir/us/breast-radiology/StructureDefinition/TumorSatelliteFragment",
  "version": "Fragment",
  "name": "TumorSatelliteFragment",
  "title": "Tumor Satellite Fragment",
  "status": "draft",
  "description": "<b>Tumor Satellite fragment</b>\n\nThis fragment adds the references for the Tumor Satellite extension.",
  "fhirVersion": "4.0.0",
  "kind": "resource",
  "abstract": true,
  "type": "Observation",
  "baseDefinition": "http://hl7.org/fhir/StructureDefinition/Observation",
  "derivation": "constraint",
  "differential": {
    "element": [
      {
        "id": "Observation",
        "path": "Observation",
        "short": "Tumor Satellite fragment",
        "definition": "This fragment adds the references for the Tumor Satellite extension.",
        "base": {
          "path": "Observation",
          "min": 0,
          "max": "*"
        }
      },
      {
        "id": "Observation.extension",
        "path": "Observation.extension",
        "slicing": {
          "discriminator": [
            {
              "type": "value",
              "path": "url"
            }
          ],
          "ordered": true,
          "rules": "openAtEnd"
        },
        "base": {
          "path": "Observation.extension",
          "min": 0,
          "max": "*"
        }
      },
      {
        "id": "Observation.extension:tumorSatellite",
        "path": "Observation.extension",
        "sliceName": "tumorSatellite",
        "short": "tumorSatellite extension",
        "definition": "This extension slice contains the tumorSatellite extension.",
        "comment": "This is one component of a group of components that comprise the observation.",
        "min": 0,
        "max": "1",
        "base": {
          "path": "Observation.extension",
          "min": 0,
          "max": "*"
        },
        "type": [
          {
            "code": "Extension",
            "profile": [
              "http://hl7.org/fhir/us/breast-radiology/StructureDefinition/TumorSatelliteExtension"
            ]
          }
        ],
        "isModifier": false
      }
    ]
  }
}