{
  "resourceType": "ValueSet",
  "id": "MassTypeValueSetVS",
  "extension": [
    {
      "url": "http://www.fragment.com/fragment",
      "valueUrl": "http://hl7.org/fhir/us/breast-radiology/StructureDefinition/HeaderFragment"
    },
    {
      "url": "http://www.fragment.com/Group",
      "valueString": "MGCodesVS"
    },
    {
      "url": "http://www.fragment.com/mapname",
      "valueString": "Mass Type/ValueSet"
    }
  ],
  "url": "http://hl7.org/fhir/us/breast-radiology/ValueSet/MassTypeValueSetVS",
  "name": "MassTypeValueSetVS",
  "title": "Mass Type ValueSet ValueSet",
  "description": "Mass type value set.",
  "compose": {
    "include": [
      {
        "system": "http://hl7.org/fhir/us/breast-radiology/CodeSystem/MassTypeCS",
        "concept": [
          {
            "code": "Solid",
            "display": "Solid Mass"
          },
          {
            "code": "PartiallySolid",
            "display": "Partially Solid Mass"
          },
          {
            "code": "Skin",
            "display": "Skin Mass"
          }
        ]
      }
    ]
  }
}